{"stats":{"minecraft:used":{"cities:laptop":24},"minecraft:custom":{"minecraft:jump":17,"minecraft:time_since_rest":1442,"minecraft:leave_game":1,"minecraft:crouch_one_cm":1751,"minecraft:damage_taken":20,"minecraft:sprint_one_cm":89,"minecraft:play_time":1442,"minecraft:time_since_death":1442,"minecraft:walk_one_cm":5097,"minecraft:sneak_time":583,"minecraft:total_world_time":1465,"minecraft:fall_one_cm":484,"minecraft:fly_one_cm":222},"minecraft:mined":{"cities:laptop":20}},"DataVersion":3105}